django_webix/.DS_Store
django_webix/__init__.py
django_webix/apps.py
django_webix/forms.py
django_webix/formsets.py
django_webix/models.py
django_webix/urls.py
django_webix/views.py
django_webix/views_autocomplete.py
django_webix/locale/it/LC_MESSAGES/django.po
django_webix/static/.DS_Store
django_webix/static/django_webix/.DS_Store
django_webix/static/django_webix/inlines.css
django_webix/static/django_webix/jquery-3.3.1.min.js
django_webix/static/django_webix/loading.gif
django_webix/static/django_webix/openmap.js
django_webix/static/django_webix/theme.siberia.css
django_webix/static/django_webix/theme.siberia.css.map
django_webix/static/django_webix/fontawesome-5.7.2/.DS_Store
django_webix/static/django_webix/fontawesome-5.7.2/css/.DS_Store
django_webix/static/django_webix/fontawesome-5.7.2/css/all.css
django_webix/static/django_webix/fontawesome-5.7.2/css/all.min.css
django_webix/static/django_webix/fontawesome-5.7.2/webfonts/fa-brands-400.eot
django_webix/static/django_webix/fontawesome-5.7.2/webfonts/fa-brands-400.svg
django_webix/static/django_webix/fontawesome-5.7.2/webfonts/fa-brands-400.ttf
django_webix/static/django_webix/fontawesome-5.7.2/webfonts/fa-brands-400.woff
django_webix/static/django_webix/fontawesome-5.7.2/webfonts/fa-brands-400.woff2
django_webix/static/django_webix/fontawesome-5.7.2/webfonts/fa-regular-400.eot
django_webix/static/django_webix/fontawesome-5.7.2/webfonts/fa-regular-400.svg
django_webix/static/django_webix/fontawesome-5.7.2/webfonts/fa-regular-400.ttf
django_webix/static/django_webix/fontawesome-5.7.2/webfonts/fa-regular-400.woff
django_webix/static/django_webix/fontawesome-5.7.2/webfonts/fa-regular-400.woff2
django_webix/static/django_webix/fontawesome-5.7.2/webfonts/fa-solid-900.eot
django_webix/static/django_webix/fontawesome-5.7.2/webfonts/fa-solid-900.svg
django_webix/static/django_webix/fontawesome-5.7.2/webfonts/fa-solid-900.ttf
django_webix-0.2.0.dist-info/DESCRIPTION.rst
django_webix-0.2.0.dist-info/METADATA
django_webix-0.2.0.dist-info/RECORD
django_webix-0.2.0.dist-info/WHEEL
django_webix-0.2.0.dist-info/metadata.json
django_webix-0.2.0.dist-info/top_level.txt
